odoo/addons/base_technical_user/README.rst
odoo/addons/base_technical_user/__init__.py
odoo/addons/base_technical_user/__manifest__.py
odoo/addons/base_technical_user/i18n/ar.po
odoo/addons/base_technical_user/i18n/base_technical_user.pot
odoo/addons/base_technical_user/i18n/de.po
odoo/addons/base_technical_user/i18n/es.po
odoo/addons/base_technical_user/i18n/fr.po
odoo/addons/base_technical_user/i18n/hr.po
odoo/addons/base_technical_user/i18n/it.po
odoo/addons/base_technical_user/i18n/nl_NL.po
odoo/addons/base_technical_user/i18n/pt.po
odoo/addons/base_technical_user/i18n/zh_CN.po
odoo/addons/base_technical_user/models/__init__.py
odoo/addons/base_technical_user/models/models.py
odoo/addons/base_technical_user/models/res_company.py
odoo/addons/base_technical_user/readme/CONTRIBUTORS.rst
odoo/addons/base_technical_user/readme/DESCRIPTION.rst
odoo/addons/base_technical_user/readme/USAGE.rst
odoo/addons/base_technical_user/static/description/icon.png
odoo/addons/base_technical_user/static/description/index.html
odoo/addons/base_technical_user/tests/__init__.py
odoo/addons/base_technical_user/tests/test_sudo_tech.py
odoo/addons/base_technical_user/views/res_company_view.xml
odoo12_addon_base_technical_user-12.0.1.1.1.dist-info/METADATA
odoo12_addon_base_technical_user-12.0.1.1.1.dist-info/WHEEL
odoo12_addon_base_technical_user-12.0.1.1.1.dist-info/top_level.txt
odoo12_addon_base_technical_user-12.0.1.1.1.dist-info/RECORD
